version_parser/__init__.py
version_parser/test.py
version_parser/version.py
version_parser-0.0.1.dist-info/LICENSE
version_parser-0.0.1.dist-info/METADATA
version_parser-0.0.1.dist-info/WHEEL
version_parser-0.0.1.dist-info/top_level.txt
version_parser-0.0.1.dist-info/RECORD
