Metadata-Version: 2.1
Name: version-parser
Version: 0.0.1
Summary: This package can parse and compare semantic versioning.
Home-page: https://github.com/eieste/VersionParser
Author: Stefan Eiermann
Author-email: pypip@ultraapp.de
License: UNKNOWN
Platform: UNKNOWN
Classifier: Programming Language :: Python :: 3
Classifier: License :: OSI Approved :: MIT License
Classifier: Operating System :: OS Independent
Classifier: Topic :: Software Development
